gamehub/__init__.py
gamehub/adivinhacao.py
gamehub/jogo_da_forca.py
gamehub/labirinto.py
gamehub/main.py
gamehub/pac_man.py
gamehub/snake.py
gamehub/space_shooter.py
gamehub/assets/alvo.png
gamehub/assets/foguete.png
gamehub/assets/forca.png
gamehub/assets/icon.png
gamehub/assets/labirinto.png
gamehub/assets/pacman.png
gamehub/assets/sair.png
gamehub/assets/snake.png
pygamehub-1.0.0.dist-info/licenses/LICENSE
pygamehub-1.0.0.dist-info/METADATA
pygamehub-1.0.0.dist-info/WHEEL
pygamehub-1.0.0.dist-info/entry_points.txt
pygamehub-1.0.0.dist-info/top_level.txt
pygamehub-1.0.0.dist-info/RECORD
